braket_daq-0.1.18.dist-info/DESCRIPTION.rst
braket_daq-0.1.18.dist-info/METADATA
braket_daq-0.1.18.dist-info/RECORD
braket_daq-0.1.18.dist-info/WHEEL
braket_daq-0.1.18.dist-info/entry_points.txt
braket_daq-0.1.18.dist-info/metadata.json
braket_daq-0.1.18.dist-info/top_level.txt
daq/__init__.py
daq/commands.py
daq/pico.py
daq/scripts.sh
