Metadata-Version: 2.0
Name: braket-daq
Version: 0.1.18
Summary: Picoscope file handling project
Home-page: https://github.com/
Author: Rob deCarvalho
Author-email: unlisted@unlisted.net
License: BSD
Keywords: picoscope
Platform: UNKNOWN
Classifier: Environment :: Console
Classifier: Intended Audience :: Science/Research
Classifier: Programming Language :: Python
Classifier: Programming Language :: Python :: 3
Classifier: Programming Language :: Python :: 3.6
Classifier: Topic :: Scientific/Engineering
Requires-Dist: gunicorn
Requires-Dist: hug
